humanlikehearing/__init__.py
humanlikehearing/asrsystem.py
humanlikehearing/dataset.py
humanlikehearing/filtertools.py
humanlikehearing/sound.py
humanlikehearing/testbattery.py
humanlikehearing/version.py
humanlikehearing/library/__init__.py
humanlikehearing/library/a_weighting.py
humanlikehearing/library/audio_format.py
humanlikehearing/library/speech_voltmeter_svp56.py
humanlikehearing/library/voice_activity_detection.py
humanlikehearing-0.1.0.dist-info/LICENSE
humanlikehearing-0.1.0.dist-info/METADATA
humanlikehearing-0.1.0.dist-info/WHEEL
humanlikehearing-0.1.0.dist-info/top_level.txt
humanlikehearing-0.1.0.dist-info/RECORD
