Metadata-Version: 2.1
Name: humanlikehearing
Version: 0.1.0
Summary: Psychometric testing on Automatic Speech Recognition systems
Home-page: https://github.com/lotteweerts/humanlikehearing
Author: Lotte Weerts
Author-email: lotteweerts@gmail.com
License: UNKNOWN
Project-URL: Bug Tracker, https://github.com/lotteweerts/humanlikehearing/issues
Platform: UNKNOWN
Classifier: Programming Language :: Python :: 3
Classifier: License :: OSI Approved :: BSD License
Classifier: Operating System :: OS Independent
Classifier: Development Status :: 3 - Alpha
Classifier: Intended Audience :: Science/Research
Classifier: Natural Language :: English
Classifier: Topic :: Scientific/Engineering :: Artificial Intelligence
Classifier: Topic :: Scientific/Engineering :: Bio-Informatics
Requires-Python: >=3.5
Requires-Dist: scipy (>=1.0.0)
Requires-Dist: numpy (>=1.15.0)
Requires-Dist: pandas (>=0.13)
Requires-Dist: absl-py (>=0.10.0)
Requires-Dist: PyPDF2 (>=1.26.0)
Requires-Dist: librosa (>=0.7.0)
Requires-Dist: nltk (>=3.5)
Requires-Dist: praat-parselmouth (>=0.3.3)
Requires-Dist: SoundFile (>=0.10.3.post1)
Requires-Dist: webrtcvad-wheels (>=2.0.10.post2)
